yappr/__init__.py
yappr/decorator.py
yappr/logger.py
yappr/py.typed
yappr/updater.py
yappr-1.0.8.dist-info/LICENSE
yappr-1.0.8.dist-info/METADATA
yappr-1.0.8.dist-info/WHEEL
yappr-1.0.8.dist-info/top_level.txt
yappr-1.0.8.dist-info/RECORD
