Metadata-Version: 2.1
Name: yappr
Version: 1.0.8
Summary: Yet another python package updater
Author-email: Pradish Bijukchhe <pradish@sandbox.com.np>
License: Copyright (c) 2018 The Python Packaging Authority
Project-URL: Homepage, https://github.com/sandbox-pokhara/yappr
Project-URL: Issues, https://github.com/sandbox-pokhara/yappr/issues
Classifier: Programming Language :: Python :: 3
Requires-Python: >=3
License-File: LICENSE
